{
  "required": true,
  "minVersion": "0.8",
  "package": "me.andrew.gravitychanger.mixin",
  "compatibilityLevel": "JAVA_17",
  "mixins": [
    "AbstractSkeletonEntityMixin",
    "AreaEffectCloudEntityMixin",
    "CrossbowItemMixin",
    "DirectionMixin",
    "DrownedEntityMixin",
    "EndCrystalEntityMixin",
    "EnderDragonEntityMixin",
    "EnderDragonPartMixin",
    "EndermanEntity$ChasePlayerGoalMixin",
    "EndermanEntityMixin",
    "EntityMixin",
    "EntityShapeContextMixin",
    "ExperianceOrbEntityMixin",
    "ExperienceBottleItemMixin",
    "ExplosionMixin",
    "FireworkRocketEntityMixin",
    "FishingBobberEntityMixin",
    "IllusionerEntityMixin",
    "ItemEntityMixin",
    "ItemMixin",
    "ItemUsageContextMixin",
    "LivingEntityMixin",
    "LookAtEntityGoalMixin",
    "LookControlMixin",
    "MobEntityMixin",
    "PersistentProjectileEntityMixin",
    "PiglinEntityMixin",
    "PillagerEntityMixin",
    "PistonBlockEntityMixin",
    "PlayerEntityMixin",
    "PlayerManagerMixin",
    "PointedDripstoneBlockMixin",
    "ProjectileEntityMixin",
    "RamImpactTaskMixin",
    "ServerPlayerEntityMixin",
    "ServerPlayerInteractionManagerMixin",
    "ServerPlayNetworkHandlerMixin",
    "ShulkerBoxBlockEntityMixin",
    "ShulkerEntityMixin",
    "SnowGolemEntityMixin",
    "ThrowablePotionItemMixin",
    "ThrownEntityMixin",
    "ThrownItemEntityMixin",
    "WitchEntityMixin",
    "WitherEntityMixin",
    "WolfBegGoalMixin"
  ],
  "client": [
    "client.BiomeEffectSoundPlayerMixin",
    "client.CameraMixin",
    "client.ClientPlayerEntityMixin",
    "client.ClientPlayNetworkHandlerMixin",
    "client.EntityRenderDispatcherMixin",
    "client.EntityRenderMixin",
    "client.FishingBobberEntityRendererMixin",
    "client.GameRendererMixin",
    "client.InGameOverlayRendererMixin",
    "client.ItemPickupParticleMixin",
    "client.OtherClientPlayerEntityMixin",
    "client.PlayerEntityRendererMixin"
  ],
  "injectors": {
    "defaultRequire": 1
  }
}
